{
  "jokes": [
    { "question": "Tại sao con mèo lại chia tay với bạn trai?", "answer": "Vì nó phát hiện anh ta là một con chuột đội lốt!" },
    { "question": "Cà phê thì đắng, còn bạn thì ngọt, vậy mình hợp nhau như gì?", "answer": "Như cà phê sữa!" },
    { "question": "Tại sao phi hành gia chia tay với bạn gái?", "answer": "Vì anh ấy cần không gian riêng!" },
    { "question": "Con cá nói gì khi đâm vào tường?", "answer": "'Đau đầu quá, quên bơi lùi!'" },
    { "question": "Tại sao cái cây lại hay bị bạn bè trêu?", "answer": "Vì nó cứ đứng im thin thít!" },
    { "question": "Môn học nào dễ nhất ở trường?", "answer": "Hóa học, vì chỉ cần có 'phản ứng' là đủ!" },
    { "question": "Tại sao quả chuối lại thích hát?", "answer": "Vì nó muốn trở thành 'chuối rốc'!" },
    { "question": "Bạn thân là gì?", "answer": "Là đứa biết bạn thích ăn gì và sẵn sàng để bạn ăn ké!" },
    { "question": "Tại sao con gà không bao giờ nói dối?", "answer": "Vì nó chỉ biết 'cục tác' sự thật!" },
    { "question": "Câu hỏi mà học sinh sợ nhất là gì?", "answer": "'Hôm nay ai chưa làm bài tập?'" },
    { "question": "Tại sao chiếc xe đạp không đi được?", "answer": "Vì nó mệt, cần 'đạp' thêm động lực!" },
    { "question": "Người yêu không có, nhưng cái gì thì phải mạnh?", "answer": "Wifi!" },
    { "question": "Tại sao con chó không làm ca sĩ?", "answer": "Vì nó chỉ biết sủa hit, không hát hit!" },
    { "question": "Cái gì càng ăn càng nhỏ đi?", "answer": "Cái bánh, vì ăn xong là hết!" },
    { "question": "Tại sao con bò lại hay cười?", "answer": "Vì nó nghe kể chuyện 'bò' đùa!" },
    { "question": "Tại sao trà sữa lại đắt?", "answer": "Vì nó chứa cả 'trân châu' lẫn tình yêu!" },
    { "question": "Cái gì bay trên trời mà không có cánh?", "answer": "Thời gian, vì nó trôi nhanh lắm!" },
    { "question": "Tại sao cái bàn lại ghét ghế?", "answer": "Vì ghế cứ được ngồi, còn bàn chỉ bị đè!" },
    { "question": "Mưa thì ướt, nắng thì khô, còn crush thì làm gì với tim mình?", "answer": "Làm tim mình 'lơ lửng'!" },
    { "question": "Tại sao con ốc sên chạy chậm?", "answer": "Vì nó mang cả 'nhà' trên lưng!" },
    { "question": "Tại sao con mèo không thích học toán?", "answer": "Vì nó ghét phải 'giải mèo' đề!" },
    { "question": "Tại sao điện thoại luôn đi với sạc?", "answer": "Vì sạc là nguồn sống, không có là 'xỉu up xỉu down'!" },
    { "question": "Tại sao cái gối được nhiều người yêu?", "answer": "Vì nó luôn 'nghe' mà không bao giờ 'nói'!" },
    { "question": "Con gì buồn nhất thế giới?", "answer": "Con wifi yếu!" },
    { "question": "Tại sao đôi dép không bao giờ cãi nhau?", "answer": "Vì nó luôn đi cùng một hướng!" },
    { "question": "Tại sao đèn đỏ không bao giờ tán tỉnh ai?", "answer": "Vì nó sợ bị 'đứng tim'!" },
    { "question": "Cái gì càng ngủ nhiều càng... mệt?", "answer": "Cái đồng hồ báo thức, vì phải thức trước người ta!" },
    { "question": "Tại sao cái giường không làm streamer?", "answer": "Vì suốt ngày 'nằm vùng'!" },
    { "question": "Tại sao con cá không chơi Facebook?", "answer": "Vì sợ bị 'thả câu'!" },
    { "question": "Trái tim và wifi khác nhau thế nào?", "answer": "Wifi mạnh làm bạn vui, tim yếu làm bạn buồn!" },
    { "question": "Tại sao con bò không dùng laptop?", "answer": "Vì mỗi lần click chuột là nó giật mình!" },
    { "question": "Tại sao thằn lằn không làm rapper?", "answer": "Vì flow của nó toàn... lắc đầu!" },
    { "question": "Tại sao cái tủ lạnh được phong thần?", "answer": "Vì nó giữ đồ cực lạnh, ai cũng nể!" },
    { "question": "Tại sao con muỗi không bao giờ tốt nghiệp?", "answer": "Vì suốt ngày đi hút chích!" },
    { "question": "Con gì không não mà vẫn suy nghĩ nhiều?", "answer": "Con tim!" },
    { "question": "Tại sao cái quần bị từ chối tình cảm?", "answer": "Vì nó quá... bó sát!" },
    { "question": "Tại sao cục tẩy không có bạn?", "answer": "Vì nó hay xóa bỏ mọi mối quan hệ!" },
    { "question": "Tại sao cái nồi không bao giờ nổi tiếng?", "answer": "Vì toàn bị đậy nắp!" },
    { "question": "Tại sao dép trái luôn buồn?", "answer": "Vì người ta hay bước chân phải trước!" },
    { "question": "Tại sao con kiến đi lạc không gọi điện?", "answer": "Vì không đủ sóng trong hang!" },
    { "question": "Tại sao con cá không làm streamer?", "answer": "Vì vừa lên sóng đã bị bắt!" },
    { "question": "Tại sao con heo không tập gym?", "answer": "Vì nó sợ lên cơ rồi bị gọi là... thịt nạc vai!" },
    { "question": "Tại sao cái chổi xin nghỉ việc?", "answer": "Vì nó chán bị quét sạch mặt đất mỗi ngày!" },
    { "question": "Tại sao con vịt không đi thi thuyết trình?", "answer": "Vì nói gì cũng bị chê là... nhảm vịt!" },
    { "question": "Tại sao cái gối bị kiện ra toà?", "answer": "Vì nó ôm quá nhiều bí mật!" },
    { "question": "Tại sao cục đá không có người yêu?", "answer": "Vì quá lạnh lùng và nặng lòng!" },
    { "question": "Tại sao cái quạt bị người yêu đá?", "answer": "Vì suốt ngày quay mặt đi chỗ khác!" },
    { "question": "Tại sao cái nồi với cái chảo không nói chuyện với nhau?", "answer": "Vì mỗi lần gặp là... sôi máu!" },
    { "question": "Tại sao bút xóa không bao giờ thành công?", "answer": "Vì cứ sai là nó lại... xóa sạch quá khứ!" },
    { "question": "Tại sao máy giặt bị trầm cảm?", "answer": "Vì ngày nào cũng quay cuồng trong mối quan hệ!" },
    { "question": "Tại sao lập trình viên không bao giờ bị lạc?", "answer": "Vì họ luôn có... code định vị!" },
    { "question": "Tại sao con robot thất tình?", "answer": "Vì crush chỉ coi nó là... công cụ!" },
    { "question": "Tại sao chiếc máy in xin nghỉ phép?", "answer": "Vì nó quá mệt mỏi khi phải... phun cảm xúc mỗi ngày!" },
    { "question": "Tại sao wifi không thích đám đông?", "answer": "Vì càng đông thì nó càng yếu đuối!" },
    { "question": "Tại sao AI không làm thơ?", "answer": "Vì nó chỉ biết... học máy, không biết học yêu!" },
    { "question": "Tại sao điện thoại không ngủ trưa?", "answer": "Vì vừa nằm xuống là có người đụng vào!" },
    { "question": "Tại sao bàn phím hay bị trầm cảm?", "answer": "Vì bị gõ suốt ngày mà chẳng ai hỏi han!" },
    { "question": "Tại sao con virus máy tính cô đơn?", "answer": "Vì ai gặp cũng tìm cách cách ly!" },
    { "question": "Tại sao Google không bao giờ cãi nhau?", "answer": "Vì nó luôn tìm ra... câu trả lời!" },
    { "question": "Tại sao tai nghe không yêu nhau?", "answer": "Vì suốt ngày... bị chia đôi ngả trái phải!" },
    { "question": "Tại sao cái gương bị đuổi khỏi lớp học?", "answer": "Vì suốt ngày soi mói người khác! 🪞" },
    { "question": "Tại sao con khủng long tuyệt chủng?", "answer": "Vì không chịu update phần mềm... 🦖💀" },
    { "question": "Tại sao não không thi đại học?", "answer": "Vì nhiều người dùng nhưng chẳng ai luyện thi cho nó! 🧠❌" },
    { "question": "Tại sao cái cân bị thất nghiệp?", "answer": "Vì ai cũng muốn sống ảo, không ai muốn sự thật! ⚖️📸" },
    { "question": "Tại sao chiếc giường hay nói đạo lý?", "answer": "Vì nó thấy bạn ngã quá nhiều rồi... mà vẫn không đứng dậy! 🛏️💭" },
    { "question": "Tại sao bộ não ghen với cái điện thoại?", "answer": "Vì cái gì bạn cũng hỏi Google, chứ không hỏi nó! 🧠➡️📱" },
    { "question": "Tại sao cái tủ lạnh biết giữ bí mật?", "answer": "Vì có bao giờ nó để lộ... đồ ăn khuya của bạn đâu! ❄️🤫" },
    { "question": "Tại sao đồng hồ bị chia tay?", "answer": "Vì nó lúc nào cũng 'giờ này giờ nọ'! ⏰💔" },
    { "question": "Tại sao con mèo không bao giờ buồn?", "answer": "Vì nó biết cách... ngủ cho quên đời! 🐱💤" },
    { "question": "Tại sao cục sạc điện thoại là tri kỷ?", "answer": "Vì chỉ cần xa nhau vài tiếng là bạn gục! 🔋⚡" }
  ]
}